{
  "project_info": {
    "project_number": "440470340999",
    "firebase_url": "https://onetoonecallsample-d1ec3.firebaseio.com",
    "project_id": "onetoonecallsample-d1ec3",
    "storage_bucket": "onetoonecallsample-d1ec3.appspot.com"
  },
  "client": [
    {
      "client_info": {
        "mobilesdk_app_id": "1:440470340999:android:8bd166367917d669deff22",
        "android_client_info": {
          "package_name": "com.onetoonecallsample"
        }
      },
      "oauth_client": [
        {
          "client_id": "440470340999-sqvee78ndn0l3nhll153babme82db07k.apps.googleusercontent.com",
          "client_type": 3
        }
      ],
      "api_key": [
        {
          "current_key": "AIzaSyDg6pT3zrld23P2psugFaksqVnUOhZqwT0"
        }
      ],
      "services": {
        "appinvite_service": {
          "other_platform_oauth_client": [
            {
              "client_id": "440470340999-sqvee78ndn0l3nhll153babme82db07k.apps.googleusercontent.com",
              "client_type": 3
            }
          ]
        }
      }
    },
    {
      "client_info": {
        "mobilesdk_app_id": "1:440470340999:android:3a764e18b9a60667deff22",
        "android_client_info": {
          "package_name": "com.stringee.onetoonecallsample"
        }
      },
      "oauth_client": [
        {
          "client_id": "440470340999-sqvee78ndn0l3nhll153babme82db07k.apps.googleusercontent.com",
          "client_type": 3
        }
      ],
      "api_key": [
        {
          "current_key": "AIzaSyDg6pT3zrld23P2psugFaksqVnUOhZqwT0"
        }
      ],
      "services": {
        "appinvite_service": {
          "other_platform_oauth_client": [
            {
              "client_id": "440470340999-sqvee78ndn0l3nhll153babme82db07k.apps.googleusercontent.com",
              "client_type": 3
            }
          ]
        }
      }
    },
    {
      "client_info": {
        "mobilesdk_app_id": "1:440470340999:android:f651197bb5c20323deff22",
        "android_client_info": {
          "package_name": "com.stringee.stringeeflutterpluginexample"
        }
      },
      "oauth_client": [
        {
          "client_id": "440470340999-sqvee78ndn0l3nhll153babme82db07k.apps.googleusercontent.com",
          "client_type": 3
        }
      ],
      "api_key": [
        {
          "current_key": "AIzaSyDg6pT3zrld23P2psugFaksqVnUOhZqwT0"
        }
      ],
      "services": {
        "appinvite_service": {
          "other_platform_oauth_client": [
            {
              "client_id": "440470340999-sqvee78ndn0l3nhll153babme82db07k.apps.googleusercontent.com",
              "client_type": 3
            }
          ]
        }
      }
    },
    {
      "client_info": {
        "mobilesdk_app_id": "1:440470340999:android:dc393282a5dc718fdeff22",
        "android_client_info": {
          "package_name": "com.stringeecallkit_reactnative"
        }
      },
      "oauth_client": [
        {
          "client_id": "440470340999-sqvee78ndn0l3nhll153babme82db07k.apps.googleusercontent.com",
          "client_type": 3
        }
      ],
      "api_key": [
        {
          "current_key": "AIzaSyDg6pT3zrld23P2psugFaksqVnUOhZqwT0"
        }
      ],
      "services": {
        "appinvite_service": {
          "other_platform_oauth_client": [
            {
              "client_id": "440470340999-sqvee78ndn0l3nhll153babme82db07k.apps.googleusercontent.com",
              "client_type": 3
            }
          ]
        }
      }
    },
    {
      "client_info": {
        "mobilesdk_app_id": "1:440470340999:android:989b9289bca59d35deff22",
        "android_client_info": {
          "package_name": "com.stringeereactnativesample"
        }
      },
      "oauth_client": [
        {
          "client_id": "440470340999-sqvee78ndn0l3nhll153babme82db07k.apps.googleusercontent.com",
          "client_type": 3
        }
      ],
      "api_key": [
        {
          "current_key": "AIzaSyDg6pT3zrld23P2psugFaksqVnUOhZqwT0"
        }
      ],
      "services": {
        "appinvite_service": {
          "other_platform_oauth_client": [
            {
              "client_id": "440470340999-sqvee78ndn0l3nhll153babme82db07k.apps.googleusercontent.com",
              "client_type": 3
            }
          ]
        }
      }
    }
  ],
  "configuration_version": "1"
}